local_tests_package/__init__.py
local_tests_package/des_cap.py
local_tests_package/driver_setup.py
local_tests_package/test_login.py
local_tests_package-1.0.0.dist-info/METADATA
local_tests_package-1.0.0.dist-info/WHEEL
local_tests_package-1.0.0.dist-info/top_level.txt
local_tests_package-1.0.0.dist-info/RECORD
