Metadata-Version: 2.1
Name: local-tests-package
Version: 1.0.0
Summary: Paquete para pruebas locales en Android con Appium y Python
Requires-Python: >=3.7
Requires-Dist: pytest
Requires-Dist: Appium-Python-Client
